README
setup.py
mdbtools/MDBcli.py
mdbtools/MDBnetrc.py
mdbtools/MDBtool.py
mdbtools/MDButils.py
mdbtools/__init__.py
mdbtools/mdbcat.py
mdbtools/mdbcp.py
mdbtools/mdbindex.py
mdbtools/mdbload.py
mdbtools/mdbls.py
mdbtools/mdbmv.py
mdbtools/mdbops.py
mdbtools/mdbquery.py
mdbtools/mdbrm.py
mdbtools/mdbstats.py
mdbtools/mdbtouch.py
mdbtools/tictoc.py
mdbtools.egg-info/PKG-INFO
mdbtools.egg-info/SOURCES.txt
mdbtools.egg-info/dependency_links.txt
mdbtools.egg-info/entry_points.txt
mdbtools.egg-info/requires.txt
mdbtools.egg-info/top_level.txt