Metadata-Version: 1.0
Name: mdbtools
Version: 0.3.13
Summary: mdbtools: Python and UNIX CLI utilities to simplify common MongoDB DevOps tasks
Home-page: https://github.com/broadinstitute/mdbtools
Author: Michael S. Noble
Author-email: mnoble@broadinstitute.org
License: UNKNOWN
Platform: UNKNOWN
